gso/__init__.py
gso/constants.py
gso/logger.py
gso/analysis/__init__.py
gso/analysis/qualitative/__init__.py
gso/analysis/qualitative/compare_patches.py
gso/analysis/qualitative/hack_detector.py
gso/analysis/qualitative/plot_hack_rates.py
gso/analysis/qualitative/run_detector.py
gso/analysis/qualitative/utils.py
gso/analysis/quantitative/__init__.py
gso/analysis/quantitative/helpers.py
gso/analysis/quantitative/plot_compute_matrix.py
gso/analysis/quantitative/plot_models.py
gso/analysis/quantitative/plot_opt1_threshold.py
gso/analysis/quantitative/plot_opt_k.py
gso/analysis/quantitative/plot_speedups.py
gso/collect/README.md
gso/collect/__init__.py
gso/collect/build_dataset.py
gso/collect/pids.py
gso/collect/utils.py
gso/collect/analysis/__init__.py
gso/collect/analysis/apis.py
gso/collect/analysis/commits.py
gso/collect/analysis/parser.py
gso/collect/analysis/prompt.py
gso/collect/analysis/retriever.py
gso/collect/analysis/utils.py
gso/collect/execute/__init__.py
gso/collect/execute/evaluate.py
gso/collect/execute/execute.py
gso/collect/execute/helpers.py
gso/collect/execute/phase1.txt
gso/collect/execute/phase2.txt
gso/collect/execute/skymgr.py
gso/collect/execute/template.yaml
gso/collect/generate/__init__.py
gso/collect/generate/args.py
gso/collect/generate/context.py
gso/collect/generate/generate.py
gso/collect/generate/harness.py
gso/collect/generate/helpers.py
gso/collect/generate/oversample.py
gso/collect/generate/prompt.py
gso/collect/scripts/augment_dataset.py
gso/collect/scripts/build_manual.py
gso/collect/scripts/merge_runs.py
gso/data/__init__.py
gso/data/commit.py
gso/data/dataset.py
gso/data/entities.py
gso/data/parsing.py
gso/data/perf.py
gso/data/problem.py
gso/data/repo.py
gso/harness/README.md
gso/harness/__init__.py
gso/harness/opt_at_k.py
gso/harness/prepare_images.py
gso/harness/run_evaluation.py
gso/harness/utils.py
gso/harness/environment/__init__.py
gso/harness/environment/docker_build.py
gso/harness/environment/docker_utils.py
gsobench-0.1.4.dist-info/METADATA
gsobench-0.1.4.dist-info/WHEEL
gsobench-0.1.4.dist-info/licenses/LICENSE
gsobench-0.1.4.dist-info/RECORD
