Metadata-Version: 2.4
Name: gsobench
Version: 0.1.4
Summary: Add your description here
License-File: LICENSE
Requires-Python: >=3.12
Requires-Dist: black>=25.9.0
Requires-Dist: datasets>=3.2.0
Requires-Dist: docker>=7.1.0
Requires-Dist: fire>=0.6.0
Requires-Dist: flask>=3.0.3
Requires-Dist: fuzzywuzzy>=0.18.0
Requires-Dist: ghapi>=1.0.6
Requires-Dist: google>=3.0.0
Requires-Dist: huggingface-hub>=0.27.0
Requires-Dist: line-profiler>=4.1.3
Requires-Dist: memory-profiler>=0.61.0
Requires-Dist: openai>=2.4.0
Requires-Dist: pebble>=5.1.3
Requires-Dist: pip>=24.2
Requires-Dist: pydantic>=2.11.7
Requires-Dist: pygithub>=2.4.0
Requires-Dist: python-levenshtein>=0.25.1
Requires-Dist: r2e-test-server>=0.1.4
Requires-Dist: rich>=13.8.0
Requires-Dist: scipy>=1.14.1
Requires-Dist: seaborn>=0.13.2
Requires-Dist: skypilot>=0.5.0
